{
  "meme_name": "后浪",
  "origin": {
    "trigger_event": "2020年五四青年节前夕B站发布《后浪》宣传片，演员何冰以‘后浪’称呼新一代青年，展示B站UP主充满活力的画面，强调年轻人拥有更好的物质条件、更广阔的视野和更自由的生活方式。",
    "platform": "B站（哔哩哔哩）",
    "precursor": "宋代留府著作《清所高益》中‘长江后浪推前浪，服侍新人换旧人’的典故，原意指晚辈和新人。"
  },
  "social_context": {
    "triggers": "视频中展示跳伞、漂流、赛车、潜水等小众运动及出国、摄影等高额开支，引发对消费主义的批评；与五四运动批判精神相悖的立意争议；B站股价上涨及大量博主整活创作。",
    "target_audience": "中国青年群体，尤其是B站用户和关注社会议题的网民。",
    "political_sensitivity": "视频被指缺乏五四运动的批判精神，回避教育、医疗、劳动权益、房价等现实矛盾，被视为‘心灵鸡汤’；引发对代际认可与青年自主性的政治隐喻讨论。",
    "backlash_events": "网友计算视频中生活成本超出普通青年承受能力；联想此前‘花呗给女儿过生日’广告；批评视频立意与五四运动‘不被老一辈认可’的本质相悖；引发‘信息对账’和群体认知差异的激烈讨论。"
  },
  "spread_phases": [
    {
      "phase": "爆发期",
      "time_range": "2020年5月初",
      "description": "视频发布后迅速走红，弹幕和评论中年轻人受到鼓舞、心潮澎湃，B站股价上涨，大量博主创作‘后浪’相关整活内容。",
      "key_figures": "何冰（演员）、B站UP主群体"
    },
    {
      "phase": "争议期",
      "time_range": "2020年5月中至6月",
      "description": "网友质疑视频展示的消费主义生活，计算开支超出普通青年承受能力；批评其与五四运动精神相悖，引发社会阶层和代际矛盾的广泛讨论。",
      "key_figures": "批评性博主、社会评论者"
    },
    {
      "phase": "沉淀期",
      "time_range": "2020年下半年至今",
      "description": "‘后浪’语义漂移，从泛指新一代青年变为特指依靠家庭优越条件实现消费自由的青年群体；成为‘信息对账’和群体认知差异的符号。",
      "key_figures": "普通青年网民、文化评论者"
    }
  ],
  "mutations": [
    {
      "name": "前浪",
      "time": "2020年5月",
      "relationship": "对‘后浪’的逆向衍生，指代老一辈或保守群体。"
    },
    {
      "name": "飞浪",
      "time": "2020年5月",
      "relationship": "对‘后浪’的戏谑变体，强调更极端的消费或生活方式。"
    },
    {
      "name": "后厨",
      "time": "2020年5月",
      "relationship": "对‘后浪’的谐音恶搞，指向底层劳动场景。"
    },
    {
      "name": "你所热爱的就是你的生活",
      "time": "2020年5月",
      "relationship": "视频中金句，被单独提取为反讽或励志口号。"
    }
  ],
  "semantic_drift": {
    "original_meaning": "新一代青年人，受认可、赞美和羡慕的群体，拥有更好的物质条件和自由生活方式。",
    "current_meaning": "依靠家庭优越条件实现消费自由的青年群体，常带贬义或讽刺色彩。",
    "drift_direction": "从正面褒义转向负面批判，强调阶层分化和消费主义批判。"
  },
  "narrative_summary": "2020年B站《后浪》宣传片因展示精英化青年生活引发消费主义批判和五四精神争议，语义从‘新一代青年’漂移至‘特权消费青年’，成为代际矛盾与信息对账的符号。",
  "social_context_hint": "视频暴露了当代中国青年群体在物质条件、社会认知和代际价值观上的深刻分裂，反映了对消费主义、阶层固化及五四运动批判精神缺失的集体焦虑。",
  "_source": "corrected_video_transcript",
  "_regenerated_at": "2026-07-03T23:41:46.268442"
}